machetli/__init__.py
machetli/environments.py
machetli/errors.py
machetli/evaluator.py
machetli/search.py
machetli/successors.py
machetli/tools.py
machetli/interview/__init__.py
machetli/interview/planning.py
machetli/interview/questions.py
machetli/pddl/__init__.py
machetli/pddl/constants.py
machetli/pddl/files.py
machetli/pddl/generators.py
machetli/pddl/visitors.py
machetli/pddl/downward/__init__.py
machetli/pddl/downward/graph.py
machetli/pddl/downward/pddl/__init__.py
machetli/pddl/downward/pddl/actions.py
machetli/pddl/downward/pddl/axioms.py
machetli/pddl/downward/pddl/conditions.py
machetli/pddl/downward/pddl/effects.py
machetli/pddl/downward/pddl/f_expression.py
machetli/pddl/downward/pddl/functions.py
machetli/pddl/downward/pddl/pddl_types.py
machetli/pddl/downward/pddl/predicates.py
machetli/pddl/downward/pddl/task_element.py
machetli/pddl/downward/pddl/tasks.py
machetli/pddl/downward/pddl_parser/__init__.py
machetli/pddl/downward/pddl_parser/lisp_parser.py
machetli/pddl/downward/pddl_parser/parsing_functions.py
machetli/pddl/downward/pddl_parser/pddl_file.py
machetli/sas/__init__.py
machetli/sas/constants.py
machetli/sas/files.py
machetli/sas/generators.py
machetli/sas/sas_tasks.py
machetli/templates/__init__.py
machetli/templates/slurm-array-job.template
machetli/templates/interview/__init__.py
machetli/templates/interview/evaluator.py.tmpl
machetli/templates/interview/run.py.tmpl
machetli-0.12.dist-info/licenses/LICENSE.md
machetli-0.12.dist-info/METADATA
machetli-0.12.dist-info/WHEEL
machetli-0.12.dist-info/entry_points.txt
machetli-0.12.dist-info/top_level.txt
machetli-0.12.dist-info/RECORD
