Metadata-Version: 2.4
Name: machetli
Version: 0.12
Summary: Locate bugs in your program
Home-page: https://github.com/aibasel/machetli
Author: Lucas Galery Käser
Author-email: lucas.galerykaeser@gmail.com
License: GPL3+
Project-URL: Documentation, https://machetli.readthedocs.io/
Classifier: Environment :: Console
Classifier: Intended Audience :: Science/Research
Classifier: License :: OSI Approved :: GNU General Public License v3 or later (GPLv3+)
Classifier: Programming Language :: Python
Classifier: Programming Language :: Python :: 3.7
Classifier: Programming Language :: Python :: 3.8
Classifier: Topic :: Scientific/Engineering
Requires-Python: >=3.7
License-File: LICENSE.md
Requires-Dist: questionary>=2.1.0
Requires-Dist: CT3>=3.4
Dynamic: author
Dynamic: author-email
Dynamic: classifier
Dynamic: description
Dynamic: description-content-type
Dynamic: home-page
Dynamic: license
Dynamic: license-file
Dynamic: project-url
Dynamic: requires-dist
Dynamic: requires-python
Dynamic: summary
